Workbook

Sheet Most Streamed Spotify Songs 202
A1: Track | B1: Artist | C1: Release Date | D1: Spotify Streams | E1: Spotify Playlist Count | F1: Spotify Popularity | G1: YouTube Views | H1: YouTube Likes | I1: TikTok Views | J1: Apple Music Playlist Count | K1: SiriusXM Spins | L1: Explicit Track | M1: Date Grouped | P1: Source transparency | S1: Nidula Elgiriyewithana. (2024). Most Streamed Spotify Songs 2024. Kaggle.Com. https://www.kaggle.com/datasets/nelgiriyewithana/most-streamed-spotify-songs-2024
A2: MILLION DOLLAR BABY | B2: Tommy Richman | C2: 45408 | D2: 390470936 | E2: 30716 | F2: 92 | G2: 84274754 | H2: 1713126 | I2: 5332281936 | J2: 210 | K2: 684 | L2: 0 | M2: =IF(YEAR(C2)<2010,"Before 2010",IF(YEAR(C2)<=2020,"2010-2020","After 2020")) -> After 2020 | P2: We downloaded this data set from Kaggle.
A3: Not Like Us | B3: Kendrick Lamar | C3: 45416 | D3: 323703884 | E3: 28113 | F3: 92 | G3: 116347040 | H3: 3486739 | I3: 208339025 | J3: 188 | K3: 3 | L3: 1 | M3: =IF(YEAR(C3)<2010,"Before 2010",IF(YEAR(C3)<=2020,"2010-2020","After 2020")) -> After 2020 | P3: https://www.kaggle.com/datasets/nelgiriyewithana/most-streamed-spotify-songs-2024
A4: i like the way you kiss me | B4: Artemas | C4: 45370 | D4: 601309283 | E4: 54331 | F4: 92 | G4: 122599116 | H4: 2228730 | I4: 3369120610 | J4: 190 | K4: 536 | L4: 0 | M4: =IF(YEAR(C4)<2010,"Before 2010",IF(YEAR(C4)<=2020,"2010-2020","After 2020")) -> After 2020
A5: Flowers | B5: Miley Cyrus | C5: 44938 | D5: 2031280633 | E5: 269802 | F5: 85 | G5: 1096100899 | H5: 10629796 | I5: 14603725994 | J5: 394 | K5: 2182 | L5: 0 | M5: =IF(YEAR(C5)<2010,"Before 2010",IF(YEAR(C5)<=2020,"2010-2020","After 2020")) -> After 2020 | P5: Key variable = | Q5: TikTok views
A6: Houdini | B6: Eminem | C6: 45443 | D6: 107034922 | E6: 7223 | F6: 88 | G6: 77373957 | H6: 3670188 | J6: 182 | K6: 1 | L6: 1 | M6: =IF(YEAR(C6)<2010,"Before 2010",IF(YEAR(C6)<=2020,"2010-2020","After 2020")) -> After 2020
A7: Lovin On Me | B7: Jack Harlow | C7: 45240 | D7: 670665438 | E7: 105892 | F7: 83 | G7: 131148091 | H7: 1392593 | I7: 2938686633 | J7: 138 | K7: 4654 | L7: 1 | M7: =IF(YEAR(C7)<2010,"Before 2010",IF(YEAR(C7)<=2020,"2010-2020","After 2020")) -> After 2020
A8: Beautiful Things | B8: Benson Boone | C8: 45309 | D8: 900158751 | E8: 73118 | F8: 86 | G8: 308723145 | H8: 4120760 | I8: 534915313 | J8: 280 | K8: 429 | L8: 0 | M8: =IF(YEAR(C8)<2010,"Before 2010",IF(YEAR(C8)<=2020,"2010-2020","After 2020")) -> After 2020 | P8: Roles
A9: Gata Only | B9: FloyyMenor | C9: 45324 | D9: 675079153 | E9: 40094 | F9: 92 | G9: 228382568 | H9: 1439495 | I9: 3804584163 | J9: 160 | K9: 30 | L9: 1 | M9: =IF(YEAR(C9)<2010,"Before 2010",IF(YEAR(C9)<=2020,"2010-2020","After 2020")) -> After 2020 | P9: Julia | Q9: My role in this data was finding the data set and creating the new variable for the date grouping.
A10: Danza Kuduro - Cover | B10: MUSIC LAB JPN | C10: 45452 | D10: 1653018119 | E10: 1 | L10: 1 | M10: =IF(YEAR(C10)<2010,"Before 2010",IF(YEAR(C10)<=2020,"2010-2020","After 2020")) -> After 2020 | P10: Jordan | Q10: I helped choose the variables that we decided to focus on in the data set.
A11: BAND4BAND (feat. Lil Baby) | B11: Central Cee | C11: 45435 | D11: 90676573 | E11: 10400 | F11: 86 | G11: 32735244 | H11: 988682 | I11: 974656200 | J11: 191 | K11: 117 | L11: 1 | M11: =IF(YEAR(C11)<2010,"Before 2010",IF(YEAR(C11)<=2020,"2010-2020","After 2020")) -> After 2020 | P11: Arham | Q11: My role in this project was to create an idea for our project using music data and confirm the variables we are using for our analysis
A12: I Had Some Help (feat. Morgan Wallen) | B12: Post Malone | C12: 45422 | D12: 250080413 | E12: 16219 | F12: 91 | G12: 32229063 | H12: 550191 | I12: 2100000 | J12: 157 | K12: 71 | L12: 1 | M12: =IF(YEAR(C12)<2010,"Before 2010",IF(YEAR(C12)<=2020,"2010-2020","After 2020")) -> After 2020
A13: The Door | B13: Teddy Swims | C13: 45457 | D13: 111155129 | E13: 2 | L13: 1 | M13: =IF(YEAR(C13)<2010,"Before 2010",IF(YEAR(C13)<=2020,"2010-2020","After 2020")) -> After 2020
A14: LUNCH | B14: Billie Eilish | C14: 45429 | D14: 221636195 | E14: 13800 | F14: 92 | G14: 40022524 | H14: 1307290 | I14: 360017000 | J14: 244 | K14: 45 | L14: 0 | M14: =IF(YEAR(C14)<2010,"Before 2010",IF(YEAR(C14)<=2020,"2010-2020","After 2020")) -> After 2020
A15: Like That | B15: Future | C15: 45373 | D15: 355186436 | E15: 43025 | F15: 88 | G15: 98081493 | H15: 1456177 | J15: 153 | K15: 3 | L15: 1 | M15: =IF(YEAR(C15)<2010,"Before 2010",IF(YEAR(C15)<=2020,"2010-2020","After 2020")) -> After 2020 | P15: Motivation and Goal | Q15: Initially, we chose to decipher a data set about music analytics because of the practical real world use of the music industry. More or less, everyone is interested in many aspects of music, including creation and consumption. Our purpose of choosing Tiktok analytics as our main variable is due to the emergence of the application as a tool to promote new artists/music, compared to other older social media platforms. We are interested in finding out the relationship between platforms such as Instagram, Soundcloud, and spotify against Tiktok and see what viable relationships we can understand from reading the patterns existing in our data set.
A16: bathroom floor | B16: Kids With Buns | C16: 44841 | D16: 297185 | E16: 277 | F16: 12 | G16: 6736502312 | H16: 16785489 | I16: 22234 | J16: 1 | L16: 0 | M16: =IF(YEAR(C16)<2010,"Before 2010",IF(YEAR(C16)<=2020,"2010-2020","After 2020")) -> After 2020
A17: LALA | B17: Myke Towers | C17: 45007 | D17: 925655569 | E17: 103605 | F17: 79 | G17: 934302031 | H17: 4294166 | I17: 7499234052 | J17: 94 | K17: 228 | L17: 1 | M17: =IF(YEAR(C17)<2010,"Before 2010",IF(YEAR(C17)<=2020,"2010-2020","After 2020")) -> After 2020
A18: Fortnight (feat. Post Malone) | B18: Taylor Swift | C18: 45400 | D18: 395433400 | E18: 12784 | F18: 89 | G18: 104673836 | H18: 2484083 | I18: 207317000 | J18: 221 | K18: 3 | L18: 0 | M18: =IF(YEAR(C18)<2010,"Before 2010",IF(YEAR(C18)<=2020,"2010-2020","After 2020")) -> After 2020 | O18: =MIN(D2:D4593) -> 1071
A19: greedy | B19: Tate McRae | C19: 45183 | D19: 1258569694 | E19: 105218 | F19: 87 | G19: 141646818 | H19: 1514837 | I19: 5456156211 | J19: 207 | K19: 3310 | L19: 1 | M19: =IF(YEAR(C19)<2010,"Before 2010",IF(YEAR(C19)<=2020,"2010-2020","After 2020")) -> After 2020
A20: BLUE | B20: Billie Eilish | C20: 45429 | D20: 91272461 | E20: 6499 | F20: 86 | G20: 16038053 | H20: 569377 | I20: 1225345800 | J20: 76 | K20: 1 | L20: 0 | M20: =IF(YEAR(C20)<2010,"Before 2010",IF(YEAR(C20)<=2020,"2010-2020","After 2020")) -> After 2020
A21: As It Was | B21: Harry Styles | C21: 44651 | D21: 3301814535 | E21: 407119 | F21: 87 | G21: 800899315 | H21: 9101589 | I21: 15405881843 | J21: 455 | K21: 4909 | L21: 0 | M21: =IF(YEAR(C21)<2010,"Before 2010",IF(YEAR(C21)<=2020,"2010-2020","After 2020")) -> After 2020
A22: Paint The Town Red | B22: Doja Cat | C22: 45142 | D22: 1065399331 | E22: 170890 | F22: 78 | G22: 240970670 | H22: 2749668 | I22: 7095564106 | J22: 158 | K22: 273 | L22: 1 | M22: =IF(YEAR(C22)<2010,"Before 2010",IF(YEAR(C22)<=2020,"2010-2020","After 2020")) -> After 2020
A23: Espresso | B23: Sabrina Carpenter | C23: 45394 | D23: 547882871 | E23: 24425 | F23: 95 | G23: 107550212 | H23: 1825761 | I23: 1379499000 | J23: 298 | K23: 236 | L23: 1 | M23: =IF(YEAR(C23)<2010,"Before 2010",IF(YEAR(C23)<=2020,"2010-2020","After 2020")) -> After 2020
A24: Danza Kuduro - Cover | B24: MUSIC LAB JPN | C24: 45433 | D24: 1655575417 | E24: 10 | L24: 1 | M24: =IF(YEAR(C24)<2010,"Before 2010",IF(YEAR(C24)<=2020,"2010-2020","After 2020")) -> After 2020
A25: TEXAS HOLD 'EM | B25: Beyoncï¿ | C25: 45332 | D25: 426700979 | E25: 34044 | F25: 86 | G25: 35724356 | H25: 437980 | I25: 6518604175 | J25: 159 | K25: 257 | L25: 1 | M25: =IF(YEAR(C25)<2010,"Before 2010",IF(YEAR(C25)<=2020,"2010-2020","After 2020")) -> After 2020
A26: Future | B26: official sound studio | C26: 45301 | E26: 1 | I26: 4306269694 | L26: 0 | M26: =IF(YEAR(C26)<2010,"Before 2010",IF(YEAR(C26)<=2020,"2010-2020","After 2020")) -> After 2020
A27: Beat Automotivo Tan Tan Tan Viral | B27: WZ Beat | C27: 44705 | D27: 7382759 | E27: 3504 | F27: 35 | G27: 4233958 | H27: 69990 | I27: 22918660728 | J27: 1 | K27: 439 | L27: 0 | M27: =IF(YEAR(C27)<2010,"Before 2010",IF(YEAR(C27)<=2020,"2010-2020","After 2020")) -> After 2020
A28: STAY (with Justin Bieber) | B28: The Kid LAROI | C28: 44386 | D28: 3107100349 | E28: 451732 | F28: 78 | G28: 1256973582 | H28: 14661425 | I28: 23712377029 | J28: 513 | K28: 4096 | L28: 1 | M28: =IF(YEAR(C28)<2010,"Before 2010",IF(YEAR(C28)<=2020,"2010-2020","After 2020")) -> After 2020
A29: Baby Shark | B29: Pinkfong | C29: 42339 | D29: 720822868 | E29: 60945 | F29: 71 | G29: 16322756555 | H29: 48757673 | I29: 6577639193 | J29: 33 | K29: 142 | L29: 0 | M29: =IF(YEAR(C29)<2010,"Before 2010",IF(YEAR(C29)<=2020,"2010-2020","After 2020")) -> 2010-2020
A30: we can't be friends (wait for your love) | B30: Ariana Grande | C30: 45359 | D30: 591068364 | E30: 26203 | F30: 87 | G30: 156882014 | H30: 3080503 | J30: 194 | K30: 32 | L30: 0 | M30: =IF(YEAR(C30)<2010,"Before 2010",IF(YEAR(C30)<=2020,"2010-2020","After 2020")) -> After 2020
A31: Numb / Encore | B31: JAY-Z | C31: 45394 | D31: 1003215671 | E31: 128 | L31: 1 | M31: =IF(YEAR(C31)<2010,"Before 2010",IF(YEAR(C31)<=2020,"2010-2020","After 2020")) -> After 2020
A32: Danza Kuduro - Cover | B32: LOVE BGM JPN | C32: 45426 | D32: 1645079292 | L32: 1 | M32: =IF(YEAR(C32)<2010,"Before 2010",IF(YEAR(C32)<=2020,"2010-2020","After 2020")) -> After 2020
A33: SHEESH | B33: BABYMONSTER | C33: 45383 | D33: 124893397 | E33: 3479 | F33: 82 | G33: 359896095 | H33: 4907193 | I33: 390081328 | J33: 36 | K33: 32 | L33: 0 | M33: =IF(YEAR(C33)<2010,"Before 2010",IF(YEAR(C33)<=2020,"2010-2020","After 2020")) -> After 2020
A34: Water | B34: Tyla | C34: 45135 | D34: 670376179 | E34: 98450 | F34: 83 | G34: 265180930 | H34: 2566846 | I34: 3932956380 | J34: 225 | K34: 1215 | L34: 0 | M34: =IF(YEAR(C34)<2010,"Before 2010",IF(YEAR(C34)<=2020,"2010-2020","After 2020")) -> After 2020
A35: Strangers | B35: Kenya Grace | C35: 45170 | D35: 750154960 | E35: 139141 | F35: 79 | G35: 118208096 | H35: 1495758 | I35: 2231749390 | J35: 163 | K35: 856 | L35: 0 | M35: =IF(YEAR(C35)<2010,"Before 2010",IF(YEAR(C35)<=2020,"2010-2020","After 2020")) -> After 2020
A36: Too Sweet | B36: Hozier | C36: 45373 | D36: 532012790 | E36: 23557 | G36: 62123098 | H36: 923733 | J36: 221 | K36: 64 | L36: 0 | M36: =IF(YEAR(C36)<2010,"Before 2010",IF(YEAR(C36)<=2020,"2010-2020","After 2020")) -> After 2020
A37: What's Love Got to Do with It - 2023 Remaster | B37: Tina Turner | C37: 45408 | D37: 479417905 | E37: 7 | L37: 0 | M37: =IF(YEAR(C37)<2010,"Before 2010",IF(YEAR(C37)<=2020,"2010-2020","After 2020")) -> After 2020
A38: A Bar Song (Tipsy) | B38: Shaboozey | C38: 45394 | D38: 311928522 | E38: 25766 | F38: 96 | G38: 62694868 | H38: 837616 | I38: 378313942 | J38: 149 | K38: 141 | L38: 1 | M38: =IF(YEAR(C38)<2010,"Before 2010",IF(YEAR(C38)<=2020,"2010-2020","After 2020")) -> After 2020
A39: Lose Control | B39: Teddy Swims | C39: 45100 | D39: 775135157 | E39: 88239 | F39: 87 | G39: 139180960 | H39: 1504385 | I39: 597513595 | J39: 215 | K39: 162 | L39: 0 | M39: =IF(YEAR(C39)<2010,"Before 2010",IF(YEAR(C39)<=2020,"2010-2020","After 2020")) -> After 2020
A40: fukumean | B40: Gunna | C40: 45092 | D40: 759998727 | E40: 188142 | F40: 80 | G40: 94699547 | H40: 1222012 | I40: 3281790327 | J40: 123 | K40: 4003 | L40: 1 | M40: =IF(YEAR(C40)<2010,"Before 2010",IF(YEAR(C40)<=2020,"2010-2020","After 2020")) -> After 2020
A41: Dance Monkey | B41: Tones And I | C41: 43595 | D41: 3071214106 | E41: 375201 | F41: 71 | G41: 3366447481 | H41: 27240268 | I41: 5861939942 | J41: 549 | K41: 169 | L41: 0 | M41: =IF(YEAR(C41)<2010,"Before 2010",IF(YEAR(C41)<=2020,"2010-2020","After 2020")) -> 2010-2020
A42: BIRDS OF A FEATHER | B42: Billie Eilish | C42: 45429 | D42: 214237645 | E42: 10871 | F42: 92 | G42: 11033725 | H42: 251373 | I42: 443104700 | J42: 247 | K42: 8 | L42: 0 | M42: =IF(YEAR(C42)<2010,"Before 2010",IF(YEAR(C42)<=2020,"2010-2020","After 2020")) -> After 2020
A43: Cupid ï¿½ï¿½ï¿½ Twin Ver. (FIFTY FIFTY) ï¿½ï¿½ï¿½ Spe | B43: sped up 8282 | C43: 45024 | D43: 170970614 | E43: 27827 | F43: 41 | G43: 22280037 | H43: 334523 | I43: 12196985599 | J43: 2 | L43: 1 | M43: =IF(YEAR(C43)<2010,"Before 2010",IF(YEAR(C43)<=2020,"2010-2020","After 2020")) -> After 2020
A44: I'm Good (Blue) | B44: David Guetta | C44: 44799 | D44: 1658229422 | E44: 262248 | F44: 83 | G44: 466080689 | H44: 4324989 | I44: 1051836430 | J44: 285 | K44: 2487 | L44: 1 | M44: =IF(YEAR(C44)<2010,"Before 2010",IF(YEAR(C44)<=2020,"2010-2020","After 2020")) -> After 2020
A45: Daylight | B45: David Kushner | C45: 45030 | D45: 1126820069 | E45: 177800 | F45: 82 | G45: 274070101 | H45: 3701289 | I45: 2578518632 | J45: 163 | K45: 96 | L45: 0 | M45: =IF(YEAR(C45)<2010,"Before 2010",IF(YEAR(C45)<=2020,"2010-2020","After 2020")) -> After 2020
A46: My Love Mine All Mine | B46: Mitski | C46: 45184 | D46: 997702304 | E46: 105927 | F46: 86 | G46: 48093111 | H46: 959175 | I46: 5469808282 | J46: 91 | K46: 2676 | L46: 0 | M46: =IF(YEAR(C46)<2010,"Before 2010",IF(YEAR(C46)<=2020,"2010-2020","After 2020")) -> After 2020
A47: Please Please Please | B47: Sabrina Carpenter | C47: 45449 | D47: 59314441 | E47: 2572 | F47: 83 | G47: 22374807 | H47: 1026097 | I47: 1200000 | J47: 199 | K47: 2 | L47: 1 | M47: =IF(YEAR(C47)<2010,"Before 2010",IF(YEAR(C47)<=2020,"2010-2020","After 2020")) -> After 2020
A48: Houdini | B48: Dua Lipa | C48: 45239 | D48: 493627071 | E48: 45300 | F48: 80 | G48: 150571504 | H48: 1575378 | I48: 386610043 | J48: 174 | K48: 405 | L48: 0 | M48: =IF(YEAR(C48)<2010,"Before 2010",IF(YEAR(C48)<=2020,"2010-2020","After 2020")) -> After 2020
A49: Danza Kuduro - Cover | B49: MUSIC LAB JPN | C49: 45414 | D49: 1655575417 | E49: 9 | L49: 1 | M49: =IF(YEAR(C49)<2010,"Before 2010",IF(YEAR(C49)<=2020,"2010-2020","After 2020")) -> After 2020
A50: If We Ever Broke Up | B50: Mae Stephens | C50: 44967 | D50: 304929492 | E50: 43923 | F50: 69 | G50: 61986821 | H50: 921044 | I50: 5684815935 | J50: 78 | K50: 822 | L50: 1 | M50: =IF(YEAR(C50)<2010,"Before 2010",IF(YEAR(C50)<=2020,"2010-2020","After 2020")) -> After 2020
A51: Despacito | B51: Luis Fonsi | C51: 42748 | D51: 1747093405 | E51: 178114 | F51: 74 | G51: 9537135721 | H51: 61799279 | I51: 1143297071 | J51: 179 | K51: 116 | L51: 0 | M51: =IF(YEAR(C51)<2010,"Before 2010",IF(YEAR(C51)<=2020,"2010-2020","After 2020")) -> 2010-2020
A52: euphoria | B52: Kendrick Lamar | C52: 45412 | D52: 168434320 | E52: 17168 | F52: 86 | G52: 53604746 | H52: 1846535 | J52: 65 | K52: 77 | L52: 1 | M52: =IF(YEAR(C52)<2010,"Before 2010",IF(YEAR(C52)<=2020,"2010-2020","After 2020")) -> After 2020
A53: Panda Basi | B53: Mvua | C53: 44967 | D53: 104271 | E53: 249 | F53: 25 | G53: 2457026781 | I53: 393580 | L53: 0 | M53: =IF(YEAR(C53)<2010,"Before 2010",IF(YEAR(C53)<=2020,"2010-2020","After 2020")) -> After 2020
A54: Calm Down (with Selena Gomez) | B54: Rema | C54: 44798 | D54: 1391688322 | E54: 163876 | F54: 77 | G54: 902742581 | H54: 8099187 | I54: 2857920 | J54: 316 | L54: 0 | M54: =IF(YEAR(C54)<2010,"Before 2010",IF(YEAR(C54)<=2020,"2010-2020","After 2020")) -> After 2020
A55: Shape of You | B55: Ed Sheeran | C55: 42741 | D55: 3909458734 | E55: 316378 | F55: 80 | G55: 8013997219 | H55: 45770887 | I55: 2320856331 | J55: 465 | K55: 282 | L55: 0 | M55: =IF(YEAR(C55)<2010,"Before 2010",IF(YEAR(C55)<=2020,"2010-2020","After 2020")) -> 2010-2020
A56: Mitu | B56: Maian | C56: 44945 | D56: 55346 | E56: 42 | F56: 13 | G56: 2432265978 | H56: 8162101 | L56: 0 | M56: =IF(YEAR(C56)<2010,"Before 2010",IF(YEAR(C56)<=2020,"2010-2020","After 2020")) -> After 2020
A57: Blinding Lights | B57: The Weeknd | C57: 43798 | D57: 4281468720 | E57: 590392 | F57: 83 | G57: 833807130 | H57: 10093211 | I57: 3501177394 | J57: 859 | K57: 1116 | L57: 0 | M57: =IF(YEAR(C57)<2010,"Before 2010",IF(YEAR(C57)<=2020,"2010-2020","After 2020")) -> 2010-2020
A58: Creepin' (with The Weeknd & 21 Savage) | B58: Metro Boomin | C58: 44897 | D58: 1337619917 | E58: 228295 | F58: 80 | G58: 193982443 | H58: 2023998 | I58: 1268862678 | J58: 152 | K58: 34 | L58: 1 | M58: =IF(YEAR(C58)<2010,"Before 2010",IF(YEAR(C58)<=2020,"2010-2020","After 2020")) -> After 2020
A59: Dona Felicidade | B59: Patati Patatï¿ | C59: 45447 | E59: 2 | G59: 52480069 | H59: 82092 | L59: 0 | M59: =IF(YEAR(C59)<2010,"Before 2010",IF(YEAR(C59)<=2020,"2010-2020","After 2020")) -> After 2020
A60: Danza Kuduro - Cover | B60: MUSIC LAB JPN | C60: 45411 | D60: 1655575417 | E60: 1 | L60: 1 | M60: =IF(YEAR(C60)<2010,"Before 2010",IF(YEAR(C60)<=2020,"2010-2020","After 2020")) -> After 2020
A61: Unholy (feat. Kim Petras) | B61: Sam Smith | C61: 44826 | D61: 1556275789 | E61: 210583 | F61: 74 | G61: 254051906 | H61: 3364206 | I61: 7945975878 | J61: 203 | K61: 117 | L61: 0 | M61: =IF(YEAR(C61)<2010,"Before 2010",IF(YEAR(C61)<=2020,"2010-2020","After 2020")) -> After 2020
A62: Stereo Love - Melodic | B62: Edward Maya | C62: 45448 | E62: 2 | F62: 9 | L62: 0 | M62: =IF(YEAR(C62)<2010,"Before 2010",IF(YEAR(C62)<=2020,"2010-2020","After 2020")) -> After 2020
A63: Very Cute Melody by Marimba Tone (39813) | B63: mitsu sound | C63: 45291 | D63: 1384 | E63: 2 | G63: 222076 | H63: 5430 | I63: 8811416708 | L63: 0 | M63: =IF(YEAR(C63)<2010,"Before 2010",IF(YEAR(C63)<=2020,"2010-2020","After 2020")) -> After 2020
A64: Supernova | B64: aespa | C64: 45425 | D64: 69729033 | E64: 2483 | F64: 81 | G64: 111310770 | H64: 1724693 | I64: 393973528 | J64: 40 | K64: 13 | L64: 0 | M64: =IF(YEAR(C64)<2010,"Before 2010",IF(YEAR(C64)<=2020,"2010-2020","After 2020")) -> After 2020
A65: Me Porto Bonito | B65: Bad Bunny | C65: 44687 | D65: 1811990630 | E65: 173358 | F65: 79 | G65: 1516863120 | H65: 8870768 | I65: 6470937272 | J65: 124 | K65: 327 | L65: 1 | M65: =IF(YEAR(C65)<2010,"Before 2010",IF(YEAR(C65)<=2020,"2010-2020","After 2020")) -> After 2020
A66: Back That Azz Up (feat. Lil Wayne & Mannie Fresh) | B66: JUVENILE | C66: 45380 | D66: 199929812 | E66: 4 | J66: 1 | L66: 1 | M66: =IF(YEAR(C66)<2010,"Before 2010",IF(YEAR(C66)<=2020,"2010-2020","After 2020")) -> After 2020
A67: Calm Down | B67: Rema | C67: 44602 | D67: 584427088 | E67: 182994 | F67: 68 | G67: 1141904909 | H67: 8766235 | I67: 18216656774 | J67: 138 | K67: 759 | L67: 0 | M67: =IF(YEAR(C67)<2010,"Before 2010",IF(YEAR(C67)<=2020,"2010-2020","After 2020")) -> After 2020
A68: CARNIVAL | B68: ýý$ | C68: 45330 | D68: 466887055 | E68: 53842 | F68: 84 | G68: 27688666 | H68: 449112 | J68: 42 | L68: 1 | M68: =IF(YEAR(C68)<2010,"Before 2010",IF(YEAR(C68)<=2020,"2010-2020","After 2020")) -> After 2020
A69: Kill Bill | B69: SZA | C69: 44903 | D69: 1873746537 | E69: 190202 | F69: 82 | G69: 220538045 | H69: 3153793 | I69: 1284413960 | J69: 214 | K69: 5448 | L69: 0 | M69: =IF(YEAR(C69)<2010,"Before 2010",IF(YEAR(C69)<=2020,"2010-2020","After 2020")) -> After 2020
A70: What Was I Made For? [From The Motion Picture "Barbie"] | B70: Billie Eilish | C70: 45120 | D70: 891720245 | E70: 114560 | F70: 82 | G70: 144741616 | H70: 2761964 | I70: 3998086216 | J70: 168 | K70: 68 | L70: 0 | M70: =IF(YEAR(C70)<2010,"Before 2010",IF(YEAR(C70)<=2020,"2010-2020","After 2020")) -> After 2020
A71: Babba | B71: Guy Mac | C71: 44988 | D71: 46567 | E71: 252 | F71: 6 | G71: 2038459981 | H71: 6076902 | J71: 2 | L71: 0 | M71: =IF(YEAR(C71)<2010,"Before 2010",IF(YEAR(C71)<=2020,"2010-2020","After 2020")) -> After 2020
A72: Heat Waves | B72: Glass Animals | C72: 44011 | D72: 2996181078 | E72: 486278 | F72: 82 | G72: 1272898075 | H72: 14947520 | I72: 5518429969 | J72: 459 | K72: 1434 | L72: 0 | M72: =IF(YEAR(C72)<2010,"Before 2010",IF(YEAR(C72)<=2020,"2010-2020","After 2020")) -> 2010-2020
A73: In the End | B73: Linkin Park | C73: 45394 | D73: 2045512421 | E73: 97 | L73: 0 | M73: =IF(YEAR(C73)<2010,"Before 2010",IF(YEAR(C73)<=2020,"2010-2020","After 2020")) -> After 2020
A74: Shakira: Bzrp Music Sessions, Vol. 53 | B74: Bizarrap | C74: 44937 | D74: 946941510 | E74: 100130 | F74: 74 | G74: 776436101 | H74: 12951756 | I74: 11936401096 | J74: 110 | K74: 180 | L74: 0 | M74: =IF(YEAR(C74)<2010,"Before 2010",IF(YEAR(C74)<=2020,"2010-2020","After 2020")) -> After 2020
A75: The Way We Move - Extended Mix | B75: PowerDress | C75: 44995 | D75: 7909 | E75: 38 | F75: 4 | G75: 1999374091 | H75: 5708577 | L75: 0 | M75: =IF(YEAR(C75)<2010,"Before 2010",IF(YEAR(C75)<=2020,"2010-2020","After 2020")) -> After 2020
A76: Old Town Road | B76: Lil Nas X | C76: 43538 | D76: 1010494713 | E76: 127393 | F76: 67 | G76: 3203314695 | H76: 41487213 | I76: 1981431049 | J76: 63 | K76: 2195 | L76: 0 | M76: =IF(YEAR(C76)<2010,"Before 2010",IF(YEAR(C76)<=2020,"2010-2020","After 2020")) -> 2010-2020
A77: un x100to | B77: Grupo Frontera | C77: 45033 | D77: 1008495696 | E77: 99381 | F77: 75 | G77: 878892413 | H77: 4425283 | I77: 1669065906 | J77: 101 | K77: 225 | L77: 0 | M77: =IF(YEAR(C77)<2010,"Before 2010",IF(YEAR(C77)<=2020,"2010-2020","After 2020")) -> After 2020
A78: Laxed ï¿½ï¿½ï¿½ Sire | B78: Jawsh 685 | C78: 43945 | E78: 10230 | G78: 12489728 | H78: 339414 | I78: 12221514692 | L78: 0 | M78: =IF(YEAR(C78)<2010,"Before 2010",IF(YEAR(C78)<=2020,"2010-2020","After 2020")) -> 2010-2020
A79: Sprinter | B79: Dave | C79: 45078 | D79: 692512930 | E79: 199828 | F79: 78 | G79: 219666692 | H79: 2332307 | I79: 1254944697 | J79: 155 | K79: 36 | L79: 1 | M79: =IF(YEAR(C79)<2010,"Before 2010",IF(YEAR(C79)<=2020,"2010-2020","After 2020")) -> After 2020
A80: CHIHIRO | B80: Billie Eilish | C80: 45429 | D80: 169410711 | E80: 11028 | F80: 90 | G80: 19402457 | H80: 997411 | J80: 185 | L80: 0 | M80: =IF(YEAR(C80)<2010,"Before 2010",IF(YEAR(C80)<=2020,"2010-2020","After 2020")) -> After 2020
A81: TQG | B81: KAROL G | C81: 44980 | D81: 1024381758 | E81: 78554 | F81: 78 | G81: 1102289596 | H81: 8953293 | I81: 248168852 | J81: 138 | K81: 38 | L81: 1 | M81: =IF(YEAR(C81)<2010,"Before 2010",IF(YEAR(C81)<=2020,"2010-2020","After 2020")) -> After 2020
A82: Perfect | B82: Ed Sheeran | C82: 42797 | D82: 2969999682 | E82: 280165 | F82: 81 | G82: 6473698897 | H82: 39632673 | I82: 7647479866 | J82: 208 | K82: 129 | L82: 0 | M82: =IF(YEAR(C82)<2010,"Before 2010",IF(YEAR(C82)<=2020,"2010-2020","After 2020")) -> 2010-2020
A83: Pepas | B83: Farruko | C83: 44371 | D83: 1500499584 | E83: 359502 | F83: 74 | G83: 1431591689 | H83: 11553088 | I83: 4067248819 | J83: 258 | K83: 438 | L83: 1 | M83: =IF(YEAR(C83)<2010,"Before 2010",IF(YEAR(C83)<=2020,"2010-2020","After 2020")) -> After 2020
A84: Peekaboo | B84: Dave Angel | C84: 44953 | D84: 8082 | E84: 63 | G84: 2055940513 | H84: 4150967 | J84: 1 | L84: 0 | M84: =IF(YEAR(C84)<2010,"Before 2010",IF(YEAR(C84)<=2020,"2010-2020","After 2020")) -> After 2020
A85: Ella Baila Sola | B85: Eslabon Armado | C85: 45001 | D85: 1215336974 | E85: 129463 | F85: 74 | G85: 701880622 | H85: 3831236 | I85: 15373104 | J85: 83 | K85: 227 | L85: 0 | M85: =IF(YEAR(C85)<2010,"Before 2010",IF(YEAR(C85)<=2020,"2010-2020","After 2020")) -> After 2020
A86: Dance The Night - From Barbie The Album | B86: Dua Lipa | C86: 45071 | D86: 860026452 | E86: 74769 | F86: 80 | G86: 173044031 | H86: 1640319 | I86: 1227837850 | J86: 7 | K86: 1100 | L86: 0 | M86: =IF(YEAR(C86)<2010,"Before 2010",IF(YEAR(C86)<=2020,"2010-2020","After 2020")) -> After 2020
A87: La Bebe - Remix | B87: Yng Lvcas | C87: 45002 | D87: 1032225805 | E87: 94887 | F87: 79 | G87: 920878032 | H87: 3118229 | I87: 2416141351 | J87: 83 | K87: 177 | L87: 1 | M87: =IF(YEAR(C87)<2010,"Before 2010",IF(YEAR(C87)<=2020,"2010-2020","After 2020")) -> After 2020
A88: redrum | B88: 21 Savage | C88: 45303 | D88: 428233003 | E88: 57311 | G88: 105148629 | H88: 1762297 | I88: 43993800 | J88: 74 | K88: 56 | L88: 1 | M88: =IF(YEAR(C88)<2010,"Before 2010",IF(YEAR(C88)<=2020,"2010-2020","After 2020")) -> After 2020
A89: Easy On Me | B89: Adele | C89: 44483 | D89: 1720918065 | E89: 209635 | F89: 73 | G89: 1194846205 | H89: 13561925 | I89: 7860224413 | J89: 325 | K89: 1316 | L89: 0 | M89: =IF(YEAR(C89)<2010,"Before 2010",IF(YEAR(C89)<=2020,"2010-2020","After 2020")) -> After 2020
A90: Titï¿½ï¿½ Me Pregu | B90: Bad Bunny | C90: 44687 | D90: 1514239759 | E90: 190692 | F90: 77 | G90: 1366181141 | H90: 9358441 | I90: 5249863696 | J90: 150 | K90: 920 | L90: 1 | M90: =IF(YEAR(C90)<2010,"Before 2010",IF(YEAR(C90)<=2020,"2010-2020","After 2020")) -> After 2020
A91: All My Life (feat. J. Cole) | B91: Lil Durk | C91: 45058 | D91: 333202114 | E91: 108322 | F91: 68 | G91: 203487345 | H91: 2084532 | I91: 748253884 | J91: 148 | K91: 146 | L91: 1 | M91: =IF(YEAR(C91)<2010,"Before 2010",IF(YEAR(C91)<=2020,"2010-2020","After 2020")) -> After 2020
A92: Anti-Hero | B92: Taylor Swift | C92: 44855 | D92: 1563224246 | E92: 117005 | F92: 80 | G92: 203259285 | H92: 3482508 | I92: 3864505972 | J92: 261 | K92: 1088 | L92: 0 | M92: =IF(YEAR(C92)<2010,"Before 2010",IF(YEAR(C92)<=2020,"2010-2020","After 2020")) -> After 2020
A93: Quevedo: Bzrp Music Sessions, Vol. 52 | B93: Bizarrap | C93: 44748 | D93: 1692951462 | E93: 209490 | F93: 78 | G93: 1132539234 | H93: 8795731 | I93: 2054826154 | J93: 99 | K93: 37 | L93: 0 | M93: =IF(YEAR(C93)<2010,"Before 2010",IF(YEAR(C93)<=2020,"2010-2020","After 2020")) -> After 2020
A94: Magnetic | B94: ILLIT | C94: 45376 | D94: 255076355 | E94: 11500 | F94: 86 | G94: 202206901 | H94: 2596912 | I94: 506476590 | J94: 67 | K94: 137 | L94: 0 | M94: =IF(YEAR(C94)<2010,"Before 2010",IF(YEAR(C94)<=2020,"2010-2020","After 2020")) -> After 2020
A95: Lollipop | B95: Darell | C95: 45135 | D95: 275349653 | E95: 37806 | F95: 70 | G95: 347506860 | H95: 1553295 | I95: 4767676439 | J95: 19 | K95: 96 | L95: 1 | M95: =IF(YEAR(C95)<2010,"Before 2010",IF(YEAR(C95)<=2020,"2010-2020","After 2020")) -> After 2020
A96: La Diabla | B96: Xavi | C96: 45262 | D96: 649404552 | E96: 27544 | F96: 83 | G96: 433839212 | H96: 2750086 | I96: 10603563 | J96: 29 | K96: 462 | L96: 0 | M96: =IF(YEAR(C96)<2010,"Before 2010",IF(YEAR(C96)<=2020,"2010-2020","After 2020")) -> After 2020
A97: Boy's a Liar Pt. 2 | B97: PinkPantheress | C97: 44960 | D97: 851085705 | E97: 129047 | F97: 70 | G97: 211810152 | H97: 2461166 | I97: 8781020473 | J97: 162 | K97: 6243 | L97: 1 | M97: =IF(YEAR(C97)<2010,"Before 2010",IF(YEAR(C97)<=2020,"2010-2020","After 2020")) -> After 2020
A98: Snooze | B98: SZA | C98: 44904 | D98: 1013350808 | E98: 108036 | F98: 84 | G98: 390677417 | H98: 2521214 | I98: 887803828 | J98: 154 | K98: 513 | L98: 1 | M98: =IF(YEAR(C98)<2010,"Before 2010",IF(YEAR(C98)<=2020,"2010-2020","After 2020")) -> After 2020
A99: BELLAKEO | B99: Peso Pluma | C99: 45267 | D99: 359803580 | E99: 26065 | F99: 86 | G99: 369321334 | H99: 1839225 | I99: 874056250 | J99: 40 | K99: 69 | L99: 1 | M99: =IF(YEAR(C99)<2010,"Before 2010",IF(YEAR(C99)<=2020,"2010-2020","After 2020")) -> After 2020
A100: Agora Hills | B100: Doja Cat | C100: 45191 | D100: 509653100 | E100: 66219 | G100: 48045203 | H100: 986278 | I100: 544437406 | J100: 80 | K100: 14 | L100: 1 | M100: =IF(YEAR(C100)<2010,"Before 2010",IF(YEAR(C100)<=2020,"2010-2020","After 2020")) -> After 2020
...

Sheet Cleaned Data
A1: Track | B1: Artist | C1: Release Date | D1: Spotify Streams | E1: Spotify Playlist Count | F1: Spotify Popularity | G1: YouTube Views | H1: YouTube Likes | I1: TikTok Views | J1: Apple Music Playlist Count | K1: SiriusXM Spins | L1: Explicit Track | M1: Date Grouped
A2: MILLION DOLLAR BABY | B2: Tommy Richman | C2: 45408 | D2: 390470936 | E2: 30716 | F2: 92 | G2: 84274754 | H2: 1713126 | I2: 5332281936 | J2: 210 | K2: 684 | L2: 0 | M2: After 2020
A3: Not Like Us | B3: Kendrick Lamar | C3: 45416 | D3: 323703884 | E3: 28113 | F3: 92 | G3: 116347040 | H3: 3486739 | I3: 208339025 | J3: 188 | K3: 3 | L3: 1 | M3: After 2020
A4: i like the way you kiss me | B4: Artemas | C4: 45370 | D4: 601309283 | E4: 54331 | F4: 92 | G4: 122599116 | H4: 2228730 | I4: 3369120610 | J4: 190 | K4: 536 | L4: 0 | M4: After 2020 | P4: =MIN(D2:D2135) -> 301362
A5: Flowers | B5: Miley Cyrus | C5: 44938 | D5: 2031280633 | E5: 269802 | F5: 85 | G5: 1096100899 | H5: 10629796 | I5: 14603725994 | J5: 394 | K5: 2182 | L5: 0 | M5: After 2020
A6: Lovin On Me | B6: Jack Harlow | C6: 45240 | D6: 670665438 | E6: 105892 | F6: 83 | G6: 131148091 | H6: 1392593 | I6: 2938686633 | J6: 138 | K6: 4654 | L6: 1 | M6: After 2020
A7: Beautiful Things | B7: Benson Boone | C7: 45309 | D7: 900158751 | E7: 73118 | F7: 86 | G7: 308723145 | H7: 4120760 | I7: 534915313 | J7: 280 | K7: 429 | L7: 0 | M7: After 2020
A8: Gata Only | B8: FloyyMenor | C8: 45324 | D8: 675079153 | E8: 40094 | F8: 92 | G8: 228382568 | H8: 1439495 | I8: 3804584163 | J8: 160 | K8: 30 | L8: 1 | M8: After 2020
A9: BAND4BAND (feat. Lil Baby) | B9: Central Cee | C9: 45435 | D9: 90676573 | E9: 10400 | F9: 86 | G9: 32735244 | H9: 988682 | I9: 974656200 | J9: 191 | K9: 117 | L9: 1 | M9: After 2020
A10: I Had Some Help (feat. Morgan Wallen) | B10: Post Malone | C10: 45422 | D10: 250080413 | E10: 16219 | F10: 91 | G10: 32229063 | H10: 550191 | I10: 2100000 | J10: 157 | K10: 71 | L10: 1 | M10: After 2020
A11: LUNCH | B11: Billie Eilish | C11: 45429 | D11: 221636195 | E11: 13800 | F11: 92 | G11: 40022524 | H11: 1307290 | I11: 360017000 | J11: 244 | K11: 45 | L11: 0 | M11: After 2020
A12: LALA | B12: Myke Towers | C12: 45007 | D12: 925655569 | E12: 103605 | F12: 79 | G12: 934302031 | H12: 4294166 | I12: 7499234052 | J12: 94 | K12: 228 | L12: 1 | M12: After 2020
A13: Fortnight (feat. Post Malone) | B13: Taylor Swift | C13: 45400 | D13: 395433400 | E13: 12784 | F13: 89 | G13: 104673836 | H13: 2484083 | I13: 207317000 | J13: 221 | K13: 3 | L13: 0 | M13: After 2020
A14: greedy | B14: Tate McRae | C14: 45183 | D14: 1258569694 | E14: 105218 | F14: 87 | G14: 141646818 | H14: 1514837 | I14: 5456156211 | J14: 207 | K14: 3310 | L14: 1 | M14: After 2020
A15: BLUE | B15: Billie Eilish | C15: 45429 | D15: 91272461 | E15: 6499 | F15: 86 | G15: 16038053 | H15: 569377 | I15: 1225345800 | J15: 76 | K15: 1 | L15: 0 | M15: After 2020
A16: As It Was | B16: Harry Styles | C16: 44651 | D16: 3301814535 | E16: 407119 | F16: 87 | G16: 800899315 | H16: 9101589 | I16: 15405881843 | J16: 455 | K16: 4909 | L16: 0 | M16: After 2020
... A322: All of Me | B322: John Legend | C322: 40909 | D322: 2382407025 | E322: 259202 | F322: 80 | G322: 3064193777 | H322: 17820289 | I322: 643209321 | J322: 295 | K322: 341 | L322: 0 | M322: 2010-2020
A323: 2055 | B323: Sleepy Hallow | C323: 44300 | D323: 811700245 | E323: 195603 | F323: 77 | G323: 168936854 | H323: 1450642 | I323: 752325431 | J323: 39 | K323: 232 | L323: 1 | M323: After 2020
A324: Bandit | B324: Don Toliver | C324: 45323 | D324: 152597421 | E324: 19834 | F324: 12 | G324: 6556571 | H324: 181948 | I324: 98100600 | J324: 27 | K324: 1312 | L324: 1 | M324: After 2020
A325: Redbone | B325: Childish Gambino | C325: 42691 | D325: 1615152539 | E325: 377159 | F325: 76 | G325: 887924965 | H325: 7755679 | I325: 430258743 | J325: 271 | K325: 137 | L325: 1 | M325: 2010-2020
A326: You Proof | B326: Morgan Wallen | C326: 44694 | D326: 644437397 | E326: 64367 | F326: 79 | G326: 141964689 | H326: 814824 | I326: 327463451 | J326: 49 | K326: 301 | L326: 0 | M326: After 2020
A327: Break My Heart | B327: Dua Lipa | C327: 43915 | D327: 1198689895 | E327: 130486 | F327: 71 | G327: 761387435 | H327: 6874611 | I327: 1509626629 | J327: 203 | K327: 348 | L327: 0 | M327: 2010-2020
A328: Shut Down | B328: BLACKPINK | C328: 44820 | D328: 654818451 | E328: 39852 | F328: 67 | G328: 633781726 | H328: 11421404 | I328: 3365539262 | J328: 34 | K328: 201 | L328: 0 | M328: After 2020
A329: MIA (feat. Drake) | B329: Bad Bunny | C329: 43384 | D329: 1318254846 | E329: 159832 | F329: 71 | G329: 1572511545 | H329: 8633372 | I329: 244589825 | J329: 163 | K329: 100 | L329: 0 | M329: 2010-2020
A330: Toosie Slide | B330: Drake | C330: 43924 | D330: 1059262917 | E330: 200623 | F330: 64 | G330: 507137305 | H330: 5604031 | I330: 3734881670 | J330: 146 | K330: 31 | L330: 1 | M330: 2010-2020
A331: MIENTRAS ME CURO DEL CORA | B331: KAROL G | C331: 44981 | D331: 426341106 | E331: 29511 | F331: 76 | G331: 304538874 | H331: 2238586 | I331: 871654140 | J331: 22 | K331: 131 | L331: 0 | M331: After 2020
A332: Ballin' (with Roddy Ricch) | B332: Mustard | C332: 43644 | D332: 907346612 | E332: 200091 | F332: 69 | G332: 372311322 | H332: 3400085 | I332: 245290801 | J332: 91 | K332: 34 | L332: 1 | M332: 2010-2020
A333: Ain't No Love In Oklahoma (From Twisters: The Album) | B333: Luke Combs | C333: 45428 | D333: 33661899 | E333: 3565 | F333: 79 | G333: 3729783 | H333: 62696 | I333: 1441200 | J333: 8 | K333: 1 | L333: 0 | M333: After 2020
A334: Vegas (From the Original Motion Picture Soundtrack ELVIS) | B334: Doja Cat | C334: 44687 | D334: 553783547 | E334: 83450 | F334: 68 | G334: 238368386 | H334: 2671201 | I334: 2994040421 | J334: 57 | K334: 1832 | L334: 1 | M334: After 2020
A335: El Merengue | B335: Marshmello | C335: 44988 | D335: 528420867 | E335: 59791 | F335: 75 | G335: 211317309 | H335: 842146 | I335: 451806178 | J335: 84 | K335: 117 | L335: 0 | M335: After 2020
... A599: Rain On Me (with Ariana Grande) | B599: Lady Gaga | C599: 43973 | D599: 1060378159 | E599: 104647 | F599: 68 | G599: 514581598 | H599: 6465409 | I599: 538854965 | J599: 320 | K599: 438 | L599: 0 | M599: 2010-2020
A600: 0.44097222 | B600: Tiï¿½ï¿ | C600: 44868 | D600: 539802784 | E600: 82093 | F600: 74 | G600: 94379586 | H600: 652780 | I600: 119710596 | J600: 187 | K600: 265 | L600: 0 | M600: After 2020
A601: One Right Now (with The Weeknd) | B601: Post Malone | C601: 44505 | D601: 631789333 | E601: 99512 | F601: 65 | G601: 182180447 | H601: 1908939 | I601: 181078488 | J601: 89 | K601: 1005 | L601: 1 | M601: After 2020
A602: A Thousand Years | B602: Christina Perri | C602: 40834 | D602: 1654956613 | E602: 177834 | F602: 77 | G602: 2989286684 | H602: 19870174 | I602: 8594414469 | J602: 94 | K602: 66 | L602: 0 | M602: 2010-2020
A603: Secreto | B603: Anuel AA | C603: 43480 | D603: 759388276 | E603: 68502 | F603: 65 | G603: 1595484197 | H603: 8161642 | I603: 543804719 | J603: 40 | K603: 15 | L603: 0 | M603: 2010-2020
A604: I Hate U | B604: SZA | C604: 44533 | D604: 456871037 | E604: 71261 | F604: 66 | G604: 142820854 | H604: 1393679 | I604: 1676387442 | J604: 105 | K604: 1324 | L604: 1 | M604: After 2020
A605: Better Now | B605: Post Malone | C605: 43217 | D605: 1953403531 | E605: 239092 | F605: 74 | G605: 48443287 | H605: 734538 | I605: 97061584 | J605: 144 | K605: 203 | L605: 1 | M605: 2010-2020
A606: Call Me Maybe | B606: Carly Rae Jepsen | C606: 40909 | D606: 1394048309 | E606: 211162 | F606: 77 | G606: 2007334200 | H606: 12223928 | I606: 367016981 | J606: 222 | K606: 967 | L606: 0 | M606: 2010-2020
A607: Piece Of Your Heart | B607: MEDUZA | C607: 43497 | D607: 995452298 | E607: 188608 | F607: 65 | G607: 464369299 | H607: 4586152 | I607: 1282810923 | J607: 255 | K607: 196 | L607: 0 | M607: 2010-2020
A608: Ram Pam Pam | B608: NATTI NATASHA | C608: 44306 | D608: 257167813 | E608: 38896 | F608: 55 | G608: 794011391 | H608: 4280865 | I608: 2167134347 | J608: 69 | K608: 176 | L608: 1 | M608: After 2020
A609: No Se Va | B609: Grupo Frontera | C609: 44679 | D609: 582023797 | E609: 48881 | F609: 70 | G609: 293059162 | H609: 1383526 | I609: 805988782 | J609: 26 | K609: 222 | L609: 0 | M609: After 2020
A610: Aesthetic | B610: Xilo | C610: 43875 | D610: 27312761 | E610: 9048 | F610: 38 | G610: 3538161 | H610: 118805 | I610: 5979843010 | J610: 6 | K610: 239 | L610: 1 | M610: 2010-2020
A611: Your Love (9PM) | B611: ATB | C611: 44211 | D611: 721002104 | E611: 146298 | F611: 71 | G611: 118729044 | H611: 952700 | I611: 81735548 | J611: 201 | K611: 220 | L611: 0 | M611: After 2020
A612: HEAT STICK | B612: Shoreline Mafia | C612: 45422 | D612: 20538101 | E612: 3675 | F612: 74 | G612: 3575151 | H612: 101311 | I612: 108700 | J612: 23 | K612: 5 | L612: 1 | M612: After 2020
... A936: Cry | B936: Benson Boone | C936: 45387 | D936: 72952792 | E936: 5724 | F936: 18 | G936: 9235207 | H936: 107668 | I936: 45173400 | J936: 26 | K936: 38 | L936: 0 | M936: After 2020
A937: 0.95833333 | B937: Maluma | C937: 43602 | D937: 719602988 | E937: 64741 | F937: 67 | G937: 1040666593 | H937: 3868761 | I937: 29561419 | J937: 71 | K937: 240 | L937: 0 | M937: 2010-2020
A938: One Call Away | B938: Charlie Puth | C938: 42237 | D938: 833094374 | E938: 74711 | F938: 69 | G938: 975631232 | H938: 6042733 | I938: 730041228 | J938: 9 | K938: 169 | L938: 0 | M938: 2010-2020
A939: Move Your Body | B939: ýýwnboss | C939: 44498 | D939: 366000029 | E939: 116490 | F939: 71 | G939: 91180099 | H939: 918683 | I939: 1275662545 | J939: 78 | K939: 288 | L939: 0 | M939: After 2020
A940: Danza Kuduro | B940: Don Omar | C940: 40179 | D940: 1656974409 | E940: 266408 | F940: 76 | G940: 597309937 | H940: 3662324 | I940: 191397624 | J940: 104 | K940: 129 | L940: 0 | M940: 2010-2020
A941: Locked Out Of Heaven | B941: Bruno Mars | C941: 40909 | D941: 2004657631 | E941: 277766 | F941: 83 | G941: 1400581749 | H941: 9714447 | I941: 91255671 | J941: 150 | K941: 291 | L941: 0 | M941: 2010-2020
A942: Party Rock Anthem | B942: LMFAO | C942: 40544 | D942: 717233625 | E942: 190770 | F942: 68 | G942: 2681563789 | H942: 13879113 | I942: 474207854 | J942: 148 | K942: 235 | L942: 0 | M942: 2010-2020
A943: Jealous | B943: Eyedress | C943: 43805 | D943: 789418331 | E943: 170553 | F943: 78 | G943: 100552408 | H943: 2069625 | I943: 1315165820 | J943: 9 | K943: 54 | L943: 0 | M943: 2010-2020
A944: Victoriaï¿½ï¿½ï¿½s | B944: Jax | C944: 44742 | D944: 161267092 | E944: 28607 | F944: 62 | G944: 60783794 | H944: 1205587 | I944: 667522423 | J944: 9 | K944: 1543 | L944: 1 | M944: After 2020
A945: Not Afraid | B945: Eminem | C945: 40301 | D945: 1012914789 | E945: 168108 | F945: 74 | G945: 2040135706 | H945: 14876226 | I945: 1528287223 | J945: 53 | K945: 8 | L945: 1 | M945: 2010-2020
A946: Bad Romance | B946: Lady Gaga | C946: 39814 | D946: 1229109018 | E946: 166904 | F946: 77 | G946: 2049116263 | H946: 11229749 | I946: 687368332 | J946: 153 | K946: 290 | L946: 1 | M946: Before 2010
A947: Just Give Me a Reason | B947: P!nk | C947: 41166 | D947: 1301573727 | E947: 145608 | F947: 78 | G947: 1898440657 | H947: 8070655 | I947: 496883852 | J947: 135 | K947: 203 | L947: 0 | M947: 2010-2020
A948: UN DIA (ONE DAY) (Feat. Tainy) | B948: J Balvin | C948: 44036 | D948: 828608384 | E948: 93376 | F948: 64 | G948: 459178965 | H948: 3337302 | I948: 54201520 | J948: 179 | K948: 2 | L948: 0 | M948: 2010-2020
A949: Fancy | B949: Iggy Azalea | C949: 41640 | D949: 724486951 | E949: 89470 | F949: 61 | G949: 1253153682 | H949: 6766774 | I949: 155148335 | J949: 132 | K949: 250 | L949: 1 | M949: 2010-2020
... A1143: One Thing At A Time | B1143: Morgan Wallen | C1143: 44897 | D1143: 249576970 | E1143: 31843 | F1143: 70 | G1143: 39198931 | H1143: 239096 | I1143: 37058831 | J1143: 20 | K1143: 46 | L1143: 0 | M1143: After 2020
A1144: 911 | B1144: Sech | C1144: 44232 | D1144: 352258962 | E1144: 68202 | F1144: 55 | G1144: 415445675 | H1144: 2300245 | I1144: 425874947 | J1144: 43 | K1144: 92 | L1144: 1 | M1144: After 2020
A1145: You Make It Easy | B1145: Jason Aldean | C1145: 43126 | D1145: 461456306 | E1145: 39872 | F1145: 5 | G1145: 149557856 | H1145: 1484925 | I1145: 48036714 | J1145: 5 | K1145: 25 | L1145: 0 | M1145: 2010-2020
A1146: Suge | B1146: DaBaby | C1146: 43525 | D1146: 647501734 | E1146: 112493 | F1146: 62 | G1146: 447330965 | H1146: 3838459 | I1146: 435082308 | J1146: 90 | K1146: 384 | L1146: 1 | M1146: 2010-2020
A1147: Money | B1147: Cardi B | C1147: 43396 | D1147: 580625472 | E1147: 62829 | F1147: 65 | G1147: 551699941 | H1147: 5832935 | I1147: 1855716339 | J1147: 73 | K1147: 223 | L1147: 1 | M1147: 2010-2020
A1148: No Type | B1148: Rae Sremmurd | C1148: 41898 | D1148: 584277301 | E1148: 124262 | F1148: 64 | G1148: 902705161 | H1148: 5564747 | I1148: 510652592 | J1148: 64 | K1148: 6 | L1148: 1 | M1148: 2010-2020
A1149: Sand In My Boots | B1149: Morgan Wallen | C1149: 44204 | D1149: 379462137 | E1149: 52985 | F1149: 72 | G1149: 144996999 | H1149: 759185 | I1149: 137402135 | J1149: 23 | K1149: 89 | L1149: 0 | M1149: After 2020
A1150: Overseas | B1150: D-Block Europe | C1150: 44518 | D1150: 216354398 | E1150: 90545 | F1150: 64 | G1150: 92356896 | H1150: 647095 | I1150: 148927892 | J1150: 14 | K1150: 10 | L1150: 1 | M1150: After 2020
A1151: Last Friday Night (T.G.I.F.) | B1151: Katy Perry | C1151: 40179 | D1151: 1144535829 | E1151: 170779 | F1151: 71 | G1151: 1604084148 | H1151: 8081370 | I1151: 592235618 | J1151: 85 | K1151: 79 | L1151: 0 | M1151: 2010-2020
A1152: Circo Loco | B1152: Drake | C1152: 44869 | D1152: 201467069 | E1152: 74719 | F1152: 65 | G1152: 20937003 | H1152: 225873 | I1152: 119899800 | J1152: 25 | K1152: 633 | L1152: 1 | M1152: After 2020
A1153: Limbo | B1153: Freddie Dredd | C1153: 44784 | D1153: 290154153 | E1153: 78735 | F1153: 68 | G1153: 23082946 | H1153: 421187 | I1153: 914597307 | J1153: 8 | K1153: 3 | L1153: 1 | M1153: After 2020
A1154: DUELE EL CORAZON | B1154: Enrique Iglesias | C1154: 42370 | D1154: 654612558 | E1154: 69811 | F1154: 63 | G1154: 1571210815 | H1154: 5796659 | I1154: 57898629 | J1154: 81 | K1154: 80 | L1154: 0 | M1154: 2010-2020
A1155: Jï¿½ï¿½lale | B1155: Bb trickz | C1155: 45414 | D1155: 23649304 | E1155: 1089 | F1155: 73 | G1155: 18261218 | H1155: 229451 | I1155: 1395100 | J1155: 5 | K1155: 85 | L1155: 0 | M1155: After 2020
A1156: A Puro Dolor | B1156: Gabito Ballesteros | C1156: 45262 | D1156: 145332157 | E1156: 8065 | F1156: 80 | G1156: 79026835 | H1156: 407599 | I1156: 670588 | J1156: 8 | K1156: 7 | L1156: 0 | M1156: After 2020
... A1358: Summertime Sadness | B1358: Lana Del Rey | C1358: 40544 | D1358: 1442872605 | E1358: 204954 | F1358: 79 | G1358: 572303765 | H1358: 6181000 | I1358: 1549975311 | J1358: 115 | K1358: 224 | L1358: 0 | M1358: 2010-2020
A1359: 0.33333333 | B1359: Nicki Nicole | C1359: 45063 | D1359: 135465283 | E1359: 20671 | F1359: 63 | G1359: 106663098 | H1359: 736558 | I1359: 500108092 | J1359: 20 | K1359: 5 | L1359: 1 | M1359: After 2020
A1360: Double Fantasy (with Future) | B1360: The Weeknd | C1360: 45037 | D1360: 180940067 | E1360: 36631 | F1360: 66 | G1360: 51093878 | H1360: 753208 | I1360: 47997951 | J1360: 31 | K1360: 27 | L1360: 1 | M1360: After 2020
A1361: Fisherrr | B1361: Cash Cobain | C1361: 45350 | D1361: 9215777 | E1361: 2816 | F1361: 28 | G1361: 12076033 | H1361: 245565 | I1361: 40589924 | J1361: 13 | K1361: 41 | L1361: 1 | M1361: After 2020
A1362: Wild as Her | B1362: Corey Kent | C1362: 44624 | D1362: 180186017 | E1362: 32769 | F1362: 66 | G1362: 36595510 | H1362: 280859 | I1362: 23448462 | J1362: 23 | K1362: 111 | L1362: 0 | M1362: After 2020
A1363: Ignorantes | B1363: Bad Bunny | C1363: 43875 | D1363: 671572185 | E1363: 88857 | F1363: 62 | G1363: 417964046 | H1363: 2807917 | I1363: 26125487 | J1363: 70 | K1363: 66 | L1363: 1 | M1363: 2010-2020
A1364: Break Free | B1364: Ariana Grande | C1364: 41640 | D1364: 899830382 | E1364: 96199 | F1364: 70 | G1364: 1288704058 | H1364: 6983846 | I1364: 371404445 | J1364: 123 | K1364: 204 | L1364: 0 | M1364: 2010-2020
A1365: Nathy Peluso: Bzrp Music Sessions, Vol. 36 | B1365: Bizarrap | C1365: 44162 | D1365: 286381494 | E1365: 54422 | F1365: 61 | G1365: 445932496 | H1365: 5316366 | I1365: 1257208158 | J1365: 37 | K1365: 52 | L1365: 0 | M1365: 2010-2020
A1366: Acapulco | B1366: Jason Derulo | C1366: 44442 | D1366: 442260324 | E1366: 67318 | F1366: 65 | G1366: 83588626 | H1366: 799248 | I1366: 310298540 | J1366: 65 | K1366: 160 | L1366: 0 | M1366: After 2020
A1367: GHOST TOWN | B1367: Benson Boone | C1367: 44484 | D1367: 382177076 | E1367: 65369 | F1367: 66 | G1367: 78537068 | H1367: 806081 | I1367: 629205287 | J1367: 46 | K1367: 115 | L1367: 0 | M1367: After 2020
A1368: Only Human | B1368: Jonas Brothers | C1368: 43623 | D1368: 508463163 | E1368: 58919 | F1368: 65 | G1368: 136979542 | H1368: 1457926 | I1368: 45970559 | J1368: 66 | K1368: 362 | L1368: 0 | M1368: 2010-2020
A1369: Feels (feat. Pharrell Williams, Katy Perry & Big Sean) | B1369: Calvin Harris | C1369: 42902 | D1369: 1120187276 | E1369: 153725 | F1369: 70 | G1369: 80920611 | H1369: 707090 | I1369: 2745676769 | J1369: 236 | K1369: 2 | L1369: 1 | M1369: 2010-2020
A1370: Viva La Vida | B1370: Coldplay | C1370: 38616 | D1370: 2102223775 | E1370: 335772 | F1370: 80 | G1370: 1412127488 | H1370: 8707376 | I1370: 2264301241 | J1370: 93 | K1370: 208 | L1370: 0 | M1370: Before 2010
A1371: Verte Ir | B1371: DJ Luian | C1371: 43552 | D1371: 550967367 | E1371: 65928 | F1371: 64 | G1371: 728468384 | H1371: 3473098 | I1371: 20847094 | J1371: 35 | K1371: 17 | L1371: 0 | M1371: 2010-2020
... A1399: Ojos Marrones | B1399: Lasso | C1399: 44715 | D1399: 370988405 | E1399: 33800 | F1399: 68 | G1399: 69184223 | H1399: 532555 | I1399: 1614554007 | J1399: 23 | K1399: 392 | L1399: 0 | M1399: After 2020
A1400: 512 | B1400: Mora | C1400: 44232 | D1400: 475820416 | E1400: 85784 | F1400: 70 | G1400: 270122797 | H1400: 1714650 | I1400: 369308687 | J1400: 30 | K1400: 76 | L1400: 1 | M1400: After 2020
A1401: Arranca (feat. Omega) | B1401: Becky G | C1401: 44995 | D1401: 161172707 | E1401: 23604 | F1401: 66 | G1401: 52352229 | H1401: 353891 | I1401: 140240096 | J1401: 48 | K1401: 534 | L1401: 0 | M1401: After 2020
A1402: Flawlï¿½ï¿½ss (feat. Lil Uzi V | B1402: Yeat | C1402: 44813 | D1402: 233573513 | E1402: 67981 | F1402: 69 | G1402: 39331190 | H1402: 479798 | I1402: 122612542 | J1402: 12 | K1402: 72 | L1402: 1 | M1402: After 2020
A1403: I'm the One | B1403: DJ Khaled | C1403: 42736 | D1403: 1257029279 | E1403: 122763 | F1403: 67 | G1403: 77475141 | H1403: 982093 | I1403: 134170742 | J1403: 143 | K1403: 28 | L1403: 1 | M1403: 2010-2020
A1404: Typa Girl | B1404: BLACKPINK | C1404: 44820 | D1404: 357054107 | E1404: 20864 | F1404: 66 | G1404: 199710937 | H1404: 2549362 | I1404: 790229870 | J1404: 5 | K1404: 14 | L1404: 1 | M1404: After 2020
A1405: Party In The U.S.A. | B1405: Miley Cyrus | C1405: 39814 | D1405: 1587114096 | E1405: 210519 | F1405: 76 | G1405: 993529828 | H1405: 4526606 | I1405: 338781002 | J1405: 185 | K1405: 578 | L1405: 0 | M1405: Before 2010
A1406: Wet Dreamz | B1406: J. Cole | C1406: 41982 | D1406: 1244864869 | E1406: 247570 | F1406: 76 | G1406: 280151086 | H1406: 2326991 | I1406: 49460597 | J1406: 18 | K1406: 29 | L1406: 1 | M1406: 2010-2020
A1407: Next Level | B1407: aespa | C1407: 44333 | D1407: 245384123 | E1407: 26925 | F1407: 68 | G1407: 514192282 | H1407: 6129641 | I1407: 693149332 | J1407: 41 | K1407: 43 | L1407: 0 | M1407: After 2020
A1408: Whiskey Glasses | B1408: Morgan Wallen | C1408: 42580 | D1408: 806728296 | E1408: 86002 | F1408: 75 | G1408: 429423484 | H1408: 1944017 | I1408: 74890093 | J1408: 39 | K1408: 8 | L1408: 0 | M1408: 2010-2020
A1409: Amor Tumbado | B1409: Natanael Cano | C1409: 43823 | D1409: 413743535 | E1409: 39980 | F1409: 73 | G1409: 420669522 | H1409: 2712590 | I1409: 152431204 | J1409: 19 | K1409: 42 | L1409: 0 | M1409: 2010-2020
A1410: New Gold (feat. Tame Impala and Bootie Brown) | B1410: Gorillaz | C1410: 44804 | D1410: 155399041 | E1410: 62013 | F1410: 60 | G1410: 32481842 | H1410: 684033 | I1410: 135832597 | J1410: 26 | K1410: 44 | L1410: 1 | M1410: After 2020
A1411: Dientes | B1411: J Balvin | C1411: 45184 | D1411: 38622215 | E1411: 13808 | F1411: 4 | G1411: 16445144 | H1411: 247700 | I1411: 59118842 | J1411: 29 | K1411: 685 | L1411: 1 | M1411: After 2020
A1412: Look Alive (feat. Drake) | B1412: BlocBoy JB | C1412: 43140 | D1412: 982424606 | E1412: 140455 | F1412: 63 | G1412: 123104265 | H1412: 916112 | I1412: 172191863 | J1412: 24 | K1412: 421 | L1412: 1 | M1412: 2010-2020
...

Sheet Descriptive Statistics
A1: Descriptive Statistics --- Most Streamed Spotify Songs 2024
A3: Continuous Variables
A4: Variable | B4: Count | C4: Mean | D4: Median | E4: Standard Deviation | F4: Minimum | G4: Maximum | H4: Range
A5: Spotify Playlist Count | B5: =COUNT('Cleaned Data'!D:D) -> 2134 | C5: =ROUND(AVERAGE('Cleaned Data'!D:D),2) -> 6.6516229e+08 | D5: =ROUND(MEDIAN('Cleaned Data'!D:D),2) -> 5.032422e+08 | E5: =STDEV('Cleaned Data'!D:D) -> 5.7500519e+08 | F5: =MIN('Cleaned Data'!D:D) -> 301362 | G5: =MAX('Cleaned Data'!D:D) -> 4281468720 | H5: =G5-F5 -> 4281167358
A6: Spotify Streams | B6: =COUNT('Cleaned Data'!E:E) -> 2134 | C6: =ROUND(AVERAGE('Cleaned Data'!E:E),2) -> 95863.87 | D6: =ROUND(MEDIAN('Cleaned Data'!E:E),2) -> 73852 | E6: =STDEV('Cleaned Data'!E:E) -> 78127.296 | F6: =MIN('Cleaned Data'!E:E) -> 311 | G6: =MAX('Cleaned Data'!E:E) -> 590392 | H6: =G6-F6 -> 590081
A7: Spotify Popularity | B7: =COUNT('Cleaned Data'!F:F) -> 2134 | C7: =ROUND(AVERAGE('Cleaned Data'!F:F),2) -> 67.6 | D7: =ROUND(MEDIAN('Cleaned Data'!F:F),2) -> 69 | E7: =STDEV('Cleaned Data'!F:F) -> 11.389449 | F7: =MIN('Cleaned Data'!F:F) -> 1 | G7: =MAX('Cleaned Data'!F:F) -> 96 | H7: =G7-F7 -> 95
A8: Youtude View | B8: =COUNT('Cleaned Data'!G:G) -> 2134 | C8: =ROUND(AVERAGE('Cleaned Data'!G:G),2) -> 5.0413873e+08 | D8: =ROUND(MEDIAN('Cleaned Data'!G:G),2) -> 2.2129037e+08 | E8: =STDEV('Cleaned Data'!G:G) -> 8.0274728e+08 | F8: =MIN('Cleaned Data'!G:G) -> 11512 | G8: =MAX('Cleaned Data'!G:G) -> 16322756555 | H8: =G8-F8 -> 16322745043
A9: Youtude Likes | B9: =COUNT('Cleaned Data'!H:H) -> 2134 | C9: =ROUND(AVERAGE('Cleaned Data'!H:H),2) -> 3885864.1 | D9: =ROUND(MEDIAN('Cleaned Data'!H:H),2) -> 2131983 | E9: =STDEV('Cleaned Data'!H:H) -> 5457870.3 | F9: =MIN('Cleaned Data'!H:H) -> 171 | G9: =MAX('Cleaned Data'!H:H) -> 62311179 | H9: =G9-F9 -> 62311008
A10: Tiktok Views | B10: =COUNT('Cleaned Data'!I:I) -> 2134 | C10: =ROUND(AVERAGE('Cleaned Data'!I:I),2) -> 1.2818925e+09 | D10: =ROUND(MEDIAN('Cleaned Data'!I:I),2) -> 345053448 | E10: =STDEV('Cleaned Data'!I:I) -> 5.3698259e+09 | F10: =MIN('Cleaned Data'!I:I) -> 312 | G10: =MAX('Cleaned Data'!I:I) -> 214843956590 | H10: =G10-F10 -> 214843956278
A11: Apple Music Playlist Count | B11: =COUNT('Cleaned Data'!J:J) -> 2134 | C11: =ROUND(AVERAGE('Cleaned Data'!J:J),2) -> 79.79 | D11: =ROUND(MEDIAN('Cleaned Data'!J:J),2) -> 53 | E11: =STDEV('Cleaned Data'!J:J) -> 82.388389 | F11: =MIN('Cleaned Data'!J:J) -> 1 | G11: =MAX('Cleaned Data'!J:J) -> 859 | H11: =G11-F11 -> 858
A12: SiriusXM Spins | B12: =COUNT('Cleaned Data'!K:K) -> 2134 | C12: =ROUND(AVERAGE('Cleaned Data'!K:K),2) -> 277.19 | D12: =ROUND(MEDIAN('Cleaned Data'!K:K),2) -> 97 | E12: =STDEV('Cleaned Data'!K:K) -> 586.02692 | F12: =MIN('Cleaned Data'!K:K) -> 1 | G12: =MAX('Cleaned Data'!K:K) -> 7098 | H12: =G12-F12 -> 7097
A14: Categorical Variables
A15: Variable | B15: Count | C15: Mode | D15: Number of Categories
A17: Explicit Songs | D17: 2
A18: Not Explicit | B18: 1280 | C18: 0
A19: Explicit | B19: 854
A20: Grand Total | B20: 2134
A22: Dates Grouped | D22: 3
A23: 2010-2020 | B23: 1041
A24: After 2020 | B24: 1042 | C24: After 2020
A25: Before 2010 | B25: 51
A26: Grand Total | B26: 2134

Sheet Frequency Table
A1: Frequency Table --- Most Streamed Spotify Songs 2024
A3: Explicit Track
A4: Category | B4: Count | C4: Relative Frequency
A5: Not Explicit (0) | B5: =COUNTIF('Cleaned Data'!L:L,0) -> 1280 | C5: =B5/B7 -> 0.59981256
A6: Explicit (1) | B6: =COUNTIF('Cleaned Data'!L:L,1) -> 854 | C6: =B6/B7 -> 0.40018744
A7: Total | B7: =SUM(B5+B6) -> 2134 | C7: =SUM(C5:C6) -> 1
A8: This reveals that approximately 60% of the songs are not explicit and 40% are explicit.
A9: Date Grouped (Release Era)
A10: Category | B10: Count | C10: Relative Frequency
A11: Before 2010 | B11: =COUNTIF('Cleaned Data'!$M$2:$M$2135,"Before 2010") -> 51 | C11: =B11/$B$14 -> 0.023898782
A12: 2010-2020 | B12: =COUNTIF('Cleaned Data'!$M$2:$M$2135,"2010-2020") -> 1041 | C12: =B12/$B$14 -> 0.48781631
A13: After 2020 | B13: =COUNTIF('Cleaned Data'!$M$2:$M$2135,"After 2020") -> 1042 | C13: =B13/$B$14 -> 0.48828491
A14: Total | B14: =B11+B12+B13 -> 2134 | C14: =SUM(C11:C13) -> 1
A15: This reveals that the categories After 2020 and 2010-2020 are split almost evenly, with both at approximately 49%.

Sheet Visuals

Sheet Commentary
A1: Assignement 3 Commentary:
A3: Question 1: Overall structure of the data: Are there any missing values, outliers, or surprising distributions? How did you have to clean the data to analyze it?
A5: Question 2: Trends or patterns you observe, if any: (E.g.: Are any categories overly dominant or underrepresented?)
A7: Question 3: Relationships you’re curious about (if any).
A9: Question 4: Initial questions or hypotheses: Based on what you see, what might you want to explore next?
A12: Answer 1: In our initial chart "Most Streamed Spotify songs 2024", several categories included entries which were completely missing from the data set. Our first step to cleaning out our data was to filter out the empty fields and remove some of the columns with highest percentage of missing fields, including: Sirius XM Spins (46% blank) and Tiktok Views (21% blank). We had to therefore drop rows (songs) with any missing variables, leaving our total dataset from 4600 songs to 2134 songs after the data was cleaned up.
A14: Answer 2: Explicit and non-explicit music in the cleaned chart have a balanced split of 40-60%, which is pretty reasonable. The only bias in our data set is against older music (pre-2010), as songs before 2010 are barely represented at 2.4% of the data. Songs from 2010-2020 and post-2020 have an even spread in the data set (48.8% each). This makes sense as the dataset was created around 2024 streaming activity, therefore songs in newer eras should have higher numbers in certain categories, especially Tiktok, since majority of the users on that application are Gen-Z. Older generations, who prefer older generation music, may also resort to different ways of consuming their music opposed from streaming, such as physical record purchases and CDs.
A16: Answer 3: According to the r values from our data set, Tiktok Views surprisingly does not have a strong correlation to the other platforms. The correlation of Tiktok to Spotify streams and Youtube views is almost zero (r = 0.04 and 0.02 respectively). In comparison, Spotify and Youtube have a significantly stronger correlation (r= 0.51). This is very important early sign, as this can prove that a song going viral on Tiktok does not necessarily correlate success in the other platforms.
A18: Answer 4: I am curious to understand further why Tiktok has a low correlation to the other platforms. Some of the questions include:
A20: 1) What are different age groups' preferred method of music consumption: (Physical records, Youtube, Paid Subscription at a Digital Streaming Platform, etc.). Once that data is found, can we see any patterns that may indicate why songs pre-2010 era do not appear in the list as much compared to the other decades. This could also show a correlation between age and our Tiktok view category, as songs specifically catered towards a certain generation might do the best in that particular method of music consumption.
A22: 2) I am still curious to know why Tiktok Views has a low correlation to the other platforms. Do laws skew data for certain platforms? For example, I know Tiktok is completely banned in India, therefore Youtube is the most popular method of music consumption for the younger generations atleast. Any musical artist would then promote their music on Reels instead of Tiktok to attract the Indian crowd, which would obviously skew our data. China on the other hand, only uses Tiktok as an official platform, banning all other platforms in the country.
A24: 3) I want to explore more on why the correlation between Spotify and Youtube is so high. What reasons or connections can we get from these applications? In what countries are these two applications specifically being used the most, and is there any correlation for that data?

Sheet Distribution Analysis
F2: Spotify Streams | H2: Spotify Playlist Count | J2: Spotify Popularity | L2: YouTube Views | N2: YouTube Likes | P2: TikTok Views | R2: Apple Music Playlist Count | T2: SiriusXM Spins
F4: Mean | G4: 6.6516229e+08 | H4: Mean | I4: 95863.866 | J4: Mean | K4: 67.596064 | L4: Mean | M4: 5.0413873e+08 | N4: Mean | O4: 3885864.1 | P4: Mean | Q4: 1.2818925e+09 | R4: Mean | S4: 79.787723 | T4: Mean | U4: 277.19306
F5: Standard Error | G5: 12447283 | H5: Standard Error | I5: 1691.2413 | J5: Standard Error | K5: 0.24655029 | L5: Standard Error | M5: 17377273 | N5: Standard Error | O5: 118147.9 | P5: Standard Error | Q5: 1.1624198e+08 | R5: Standard Error | S5: 1.7834823 | T5: Standard Error | U5: 12.685873
F6: Median | G6: 5.032422e+08 | H6: Median | I6: 73852 | J6: Median | K6: 69 | L6: Median | M6: 2.2129037e+08 | N6: Median | O6: 2131983 | P6: Median | Q6: 345053448 | R6: Median | S6: 53 | T6: Median | U6: 97
F7: Mode | G7: 860026452 | H7: Mode | I7: 212406 | J7: Mode | K7: 70 | L7: Mode | M7: 30913276 | N7: Mode | O7: 159791 | P7: Mode | Q7: 117505652 | R7: Mode | S7: 18 | T7: Mode | U7: 1
F8: Standard Deviation | G8: 5.7500519e+08 | H8: Standard Deviation | I8: 78127.296 | J8: Standard Deviation | K8: 11.389449 | L8: Standard Deviation | M8: 8.0274728e+08 | N8: Standard Deviation | O8: 5457870.3 | P8: Standard Deviation | Q8: 5.3698259e+09 | R8: Standard Deviation | S8: 82.388389 | T8: Standard Deviation | U8: 586.02692
F9: Sample Variance | G9: 3.3063097e+17 | H9: Sample Variance | I9: 6.1038744e+09 | J9: Sample Variance | K9: 129.71955 | L9: Sample Variance | M9: 6.4440319e+17 | N9: Sample Variance | O9: 2.9788348e+13 | P9: Sample Variance | Q9: 2.883503e+19 | R9: Sample Variance | S9: 6787.8466 | T9: Sample Variance | U9: 343427.55
F10: Kurtosis | G10: 3.0777639 | H10: Kurtosis | I10: 2.3425474 | J10: Kurtosis | K10: 10.784329 | L10: Kurtosis | M10: 87.549381 | N10: Kurtosis | O10: 24.922605 | P10: Kurtosis | Q10: 1181.7072 | R10: Kurtosis | S10: 8.9357591 | T10: Kurtosis | U10: 46.376826
F11: Skewness | G11: 1.5423746 | H11: Skewness | I11: 1.3874891 | J11: Skewness | K11: -2.4826717 | L11: Skewness | M11: 6.4528702 | N11: Skewness | O11: 3.9867483 | P11: Skewness | Q11: 30.578645 | R11: Skewness | S11: 2.3576202 | T11: Skewness | U11: 5.8328636
F12: Range | G12: 4281167358 | H12: Range | I12: 590081 | J12: Range | K12: 95 | L12: Range | M12: 16322745043 | N12: Range | O12: 62311008 | P12: Range | Q12: 214843956278 | R12: Range | S12: 858 | T12: Range | U12: 7097
F13: Minimum | G13: 301362 | H13: Minimum | I13: 311 | J13: Minimum | K13: 1 | L13: Minimum | M13: 11512 | N13: Minimum | O13: 171 | P13: Minimum | Q13: 312 | R13: Minimum | S13: 1 | T13: Minimum | U13: 1
F14: Maximum | G14: 4281468720 | H14: Maximum | I14: 590392 | J14: Maximum | K14: 96 | L14: Maximum | M14: 16322756555 | N14: Maximum | O14: 62311179 | P14: Maximum | Q14: 214843956590 | R14: Maximum | S14: 859 | T14: Maximum | U14: 7098
F15: Sum | G15: 1419456334356 | H15: Sum | I15: 204573489 | J15: Sum | K15: 144250 | L15: Sum | M15: 1075832040116 | N15: Sum | O15: 8292434065 | P15: Sum | Q15: 2735558496641 | R15: Sum | S15: 170267 | T15: Sum | U15: 591530
F16: Count | G16: 2134 | H16: Count | I16: 2134 | J16: Count | K16: 2134 | L16: Count | M16: 2134 | N16: Count | O16: 2134 | P16: Count | Q16: 2134 | R16: Count | S16: 2134 | T16: Count | U16: 2134
T20: Youtube Likes
I21: Spotify Streams | T21: Mean | U21: =O4 -> 3885864.1
I22: Mean | J22: =G4 -> 6.6516229e+08 | T22: Median | U22: =O6 -> 2131983
I23: Median | J23: =G6 -> 5.032422e+08 | T23: Std Dev | U23: =O8 -> 5457870.3
I24: Std Dev | J24: =G8 -> 5.7500519e+08 | T24: Skewness | U24: =O11 -> 3.9867483
I25: Skewness | J25: =G11 -> 1.5423746 | T25: Kurtosis | U25: =O10 -> 24.922605
I26: Kurtosis | J26: =G10 -> 3.0777639
I28: This variable is skewed right which is consistent with the higher mean than median and the positive skewness.
T33: Tik Tok Views
I34: Spotify Playlist Count | T34: Mean | U34: =Q4 -> 1.2818925e+09
I35: Mean | J35: =I4 -> 95863.866 | T35: Median | U35: =Q6 -> 345053448
I36: Median | J36: =I6 -> 73852 | T36: Std Dev | U36: =Q8 -> 5.3698259e+09
I37: Std Dev | J37: =I8 -> 78127.296 | T37: Skewness | U37: =Q11 -> 30.578645
I38: Skewness | J38: =I11 -> 1.3874891 | T38: Kurtosis | U38: =Q10 -> 1181.7072
I39: Kurtosis | J39: =I10 -> 2.3425474
T40: This variable is skewed right which is consistent with the higher mean than median and the positive skewness. This would mean that this variable is not normal.
I41: This variable is skewed right which is consistent with the higher mean than median and the positive skewness. This would mean that this variable is not normal.
I46: Spotify Popularity Count | T46: Apple Music Playlist Count
I47: Mean | J47: =K4 -> 67.596064 | T47: Mean | U47: =S4 -> 79.787723
I48: Median | J48: =K6 -> 69 | T48: Median | U48: =S6 -> 53
I49: Std Dev | J49: =K8 -> 11.389449 | T49: Std Dev | U49: =S8 -> 82.388389
I50: Skewness | J50: =K11 -> -2.4826717 | T50: Skewness | U50: =S11 -> 2.3576202
I51: Kurtosis | J51: =K10 -> 10.784329 | T51: Kurtosis | U51: =S10 -> 8.9357591
I53: This variable is skewed right which is consistent with the higher median than mean and the negative skewness. This would mean that this variable is not normal. | T53: This variable is skewed right which is consistent with the higher mean than median and the positive skewness. This would mean that this variable is not normal.
T58: SiriusXM Spins
I59: Youtube Views | T59: Mean | U59: =U4 -> 277.19306
I60: Mean | J60: =M4 -> 5.0413873e+08 | T60: Median | U60: =U6 -> 97
I61: Median | J61: =M6 -> 2.2129037e+08 | T61: Std Dev | U61: =U8 -> 586.02692
I62: Std Dev | J62: =M8 -> 8.0274728e+08 | T62: Skewness | U62: =U11 -> 5.8328636
I63: Skewness | J63: =M11 -> 6.4528702 | T63: Kurtosis | U63: =U10 -> 46.376826
I64: Kurtosis | J64: =M10 -> 87.549381
T65: This variable is skewed right which is consistent with the higher mean than median and the positive skewness. This would mean that this variable is not normal.
I66: This variable is skewed right which is consistent with the higher mean than median and the positive skewness. This would mean that this variable is not normal.

Sheet Real-World Probability
A1: Probability Scenarios — Spotify Popularity Score
A3: Variable chosen:
A4: Why this variable:
A6: Distribution check
A7: Count (n)
A8: Mean
A9: Median
A10: Standard Deviation (sample)
A11: Skewness
A12: Conclusion
A14: Problem 1
A15: Problem statement:
... A22: Problem statement:
A23: Method used: | B23: Empirical distribution (percentile/relative frequency), because the variable is non-normal.
A24: Count where score < 50:
A25: Final probability answer:
A26: Explanation:
A28: Problem 3
A29: Problem statement:
A30: Method used: | B30: Empirical distribution (percentile/relative frequency), because the variable is non-normal.
A31: Count where 60 <= score <= 80:
A32: Final probability answer:
A33: Explanation:
A35: GenAI Usage & Citation
A36: How GenAI was used:
A37: Citation: | B37: Anthropic. (2026). Claude (Sonnet, July 26, 2026 version) [Large language model]. https://claude.ai

Sheet Probability Commentary
A1: Probability Commentary:
A2: Our eight continuous variables in the dataset did not come close to a normal distribution surprisingly, as the skewness ranged from -2.48 for certain variables to as high as 30.58 (for the Tiktok Views). Every variable also had a kurtosis score above 3, meaning heavy tails and clustering compared to the bell shaped curve of a normal distribution chart. With that being said, we need to hold a higher regard for the spotify popularity column in our cleaned data, even though we had initally gave less importance to this variable. Those scores still give us real world meaning to use towards practical decisions. We know that 5.7% of the total songs score above 80% in popularity, which sets a realistic standard for what data behind a successful song release should appear as and paints a picture for music labels developing a new artist. 82% of the total songs are in the popularity range of 60-80% range. A music label who has invested in an artist, should probably expect atleast 60% in terms of popularity rank in order to continue investing. Any artist who consistently misses the 60% mark may not be the "global star" the label was expecting at first. Anyone below 60% obviously has done a significant job by even making it to this chart, but may possibly be a "one hit wonder" or may not be able to reach their potential successfully.
